Data/Metrics.py
Data/Preprocessing.py
Data/_DataReader.py
Data/__init__.py
DeepLearning/Model.py
DeepLearning/__init__.py
DeepLearning/Callbacks/_BackUp.py
DeepLearning/Callbacks/_BaseCallback.py
DeepLearning/Callbacks/_EarlyStopping.py
DeepLearning/Callbacks/_ReduceLROnPlateau.py
DeepLearning/Callbacks/__init__.py
DeepLearning/Initialisers/_Initialiser.py
DeepLearning/Initialisers/_Kaiming_He.py
DeepLearning/Initialisers/_Xavier_Glorot.py
DeepLearning/Initialisers/__init__.py
DeepLearning/Layers/_Add.py
DeepLearning/Layers/_Attention.py
DeepLearning/Layers/_BaseLayer.py
DeepLearning/Layers/_Bidirectional.py
DeepLearning/Layers/_Conv2D.py
DeepLearning/Layers/_Dense.py
DeepLearning/Layers/_DenseKAN.py
DeepLearning/Layers/_Flatten.py
DeepLearning/Layers/_Identity.py
DeepLearning/Layers/_Input.py
DeepLearning/Layers/_LSTM.py
DeepLearning/Layers/_LayerList.py
DeepLearning/Layers/_MaxPooling2D.py
DeepLearning/Layers/_RNN.py
DeepLearning/Layers/_Reshape.py
DeepLearning/Layers/__init__.py
DeepLearning/Layers/Activations/_Activation.py
DeepLearning/Layers/Activations/_ReLU.py
DeepLearning/Layers/Activations/_Sigmoid.py
DeepLearning/Layers/Activations/_SoftMax.py
DeepLearning/Layers/Activations/_Tanh.py
DeepLearning/Layers/Activations/__init__.py
DeepLearning/Layers/Regularisation/_BaseRegularisation.py
DeepLearning/Layers/Regularisation/_BatchNormalisation.py
DeepLearning/Layers/Regularisation/_Dropout.py
DeepLearning/Layers/Regularisation/_GroupNormalisation.py
DeepLearning/Layers/Regularisation/_InstanceNormalisation.py
DeepLearning/Layers/Regularisation/_LayerNormalisation.py
DeepLearning/Layers/Regularisation/__init__.py
DeepLearning/Losses/_BCE.py
DeepLearning/Losses/_BaseLoss.py
DeepLearning/Losses/_CCE.py
DeepLearning/Losses/_Exponential.py
DeepLearning/Losses/_Huber.py
DeepLearning/Losses/_MAE.py
DeepLearning/Losses/_MSE.py
DeepLearning/Losses/__init__.py
DeepLearning/Optimisers/_ADADELTA.py
DeepLearning/Optimisers/_ADAGRAD.py
DeepLearning/Optimisers/_ADAM.py
dll_lib-1.0.dist-info/licenses/LICENSE
dll_lib-1.0.dist-info/METADATA
dll_lib-1.0.dist-info/WHEEL
dll_lib-1.0.dist-info/top_level.txt
dll_lib-1.0.dist-info/RECORD
